MLMCPy/__init__.py
MLMCPy/input/Input.py
MLMCPy/input/InputFromData.py
MLMCPy/input/RandomInput.py
MLMCPy/input/__init__.py
MLMCPy/mlmc/MLMCSimulator.py
MLMCPy/mlmc/__init__.py
MLMCPy/model/CDFWrapperModel.py
MLMCPy/model/CovarianceWrapperModel.py
MLMCPy/model/Model.py
MLMCPy/model/ModelFromData.py
MLMCPy/model/__init__.py
MLMCPy-0.1.0.dist-info/LICENSE
MLMCPy-0.1.0.dist-info/METADATA
MLMCPy-0.1.0.dist-info/WHEEL
MLMCPy-0.1.0.dist-info/top_level.txt
MLMCPy-0.1.0.dist-info/RECORD
