Metadata-Version: 2.1
Name: MLMCPy
Version: 0.1.0
Summary: Multi-Level Monte Carlo with Python
Home-page: https://github.com/NASA/MLMCPy
Author: James Warner 
Author-email: james.e.warner@nasa.gov
License: UNKNOWN
Platform: UNKNOWN
Classifier: Programming Language :: Python :: 2.7
Classifier: License :: OSI Approved :: Apache Software License
Classifier: Operating System :: OS Independent
Requires-Dist: numpy
Requires-Dist: scipy
